setup.py
TwitterMonitor.egg-info/PKG-INFO
TwitterMonitor.egg-info/SOURCES.txt
TwitterMonitor.egg-info/dependency_links.txt
TwitterMonitor.egg-info/requires.txt
TwitterMonitor.egg-info/top_level.txt
twitter_monitor/__init__.py
twitter_monitor/common.py
twitter_monitor/core.py