Metadata-Version: 1.1
Name: TwitterMonitor
Version: 0.1.5
Summary: Small library to create monitoring routines with Twitter DM. (Python 2.x)
Home-page: https://github.com/alissonperez/TwitterMonitor
Author: Alisson R. Perez
Author-email: alissonperez@gmail.com
License: UNKNOWN
Platform: UNKNOWN
Classifier: Programming Language :: Python :: 2 :: Only
Classifier: Development Status :: 2 - Pre-Alpha
Classifier: Operating System :: MacOS
Classifier: Operating System :: Unix
Classifier: Environment :: Console
Classifier: Intended Audience :: Developers
Classifier: Intended Audience :: System Administrators
Classifier: Intended Audience :: Information Technology
Classifier: Topic :: Software Development :: Libraries
Classifier: Topic :: System :: Monitoring
Classifier: Topic :: Utilities
